README.md
setup.py
invoicing/__init__.py
invoicing/invoice.py
invoicing_pdf_testing_and_learning.egg-info/PKG-INFO
invoicing_pdf_testing_and_learning.egg-info/SOURCES.txt
invoicing_pdf_testing_and_learning.egg-info/dependency_links.txt
invoicing_pdf_testing_and_learning.egg-info/requires.txt
invoicing_pdf_testing_and_learning.egg-info/top_level.txt